{"list": [{"이용일": "20190701", "결제일": "", "금액": "1700", "포인트리금액": "", "대분류": "생활", "중분류": "편의점", "소분류": "CU"}, {"이용일": "20190702", "결제일": "", "금액": "3500", "포인트리금액": "", "대분류": "식사", "중분류": "분식", "소분류": ""}, {"이용일": "20190703", "결제일": "", "금액": "176000", "포인트리금액": "70", "대분류": "쇼핑", "중분류": "온라인", "소분류": "옥션"}, {"이용일": "20190703", "결제일": "", "금액": "1900", "포인트리금액": "19", "대분류": "식사", "중분류": "카페", "소분류": "카페7그램"}, {"이용일": "20190703", "결제일": "", "금액": "2400", "포인트리금액": "", "대분류": "생활", "중분류": "마트", "소분류": "이마트"}, {"이용일": "20190705", "결제일": "", "금액": "1800", "포인트리금액": "", "대분류": "생활", "중분류": "편의점", "소분류": "바이더웨이"}, {"이용일": "20190705", "결제일": "", "금액": "1900", "포인트리금액": "19", "대분류": "식사", "중분류": "카페", "소분류": "카페7그램"}, {"이용일": "20190705", "결제일": "", "금액": "6900", "포인트리금액": "", "대분류": "식사", "중분류": "순대", "소분류": ""}, {"이용일": "20190706", "결제일": "", "금액": "13200", "포인트리금액": "", "대분류": "식사", "중분류": "햄버거", "소분류": "롯데리아"}, {"이용일": "20190706", "결제일": "", "금액": "11000", "포인트리금액": "", "대분류": "식사", "중분류": "카페", "소분류": "카페베네"}, {"이용일": "20190706", "결제일": "", "금액": "25000", "포인트리금액": "", "대분류": "식사", "중분류": "일식", "소분류": ""}, {"이용일": "20190706", "결제일": "", "금액": "1200", "포인트리금액": "", "대분류": "생활", "중분류": "편의점", "소분류": "GS25"}, {"이용일": "20190706", "결제일": "", "금액": "4000", "포인트리금액": "", "대분류": "식사", "중분류": "떡볶이", "소분류": ""}, {"이용일": "20190707", "결제일": "", "금액": "17800", "포인트리금액": "", "대분류": "식사", "중분류": "디저트", "소분류": ""}, {"이용일": "20190707", "결제일": "", "금액": "53000", "포인트리금액": "", "대분류": "식사", "중분류": "한식", "소분류": ""}, {"이용일": "20190707", "결제일": "", "금액": "-415", "포인트리금액": "", "대분류": "기타", "중분류": "할인", "소분류": ""}, {"이용일": "20190707", "결제일": "20190718", "금액": "4150", "포인트리금액": "", "대분류": "교통", "중분류": "지하철 4", "소분류": ""}, {"이용일": "20190708", "결제일": "", "금액": "1900", "포인트리금액": "19", "대분류": "식사", "중분류": "카페", "소분류": "카페7그램"}, {"이용일": "20190710", "결제일": "", "금액": "4326850", "포인트리금액": "", "대분류": "생활", "중분류": "전자", "소분류": "애플"}, {"이용일": "20190711", "결제일": "", "금액": "2000", "포인트리금액": "20", "대분류": "식사", "중분류": "카페", "소분류": "카페7그램"}, {"이용일": "20190712", "결제일": "", "금액": "2000", "포인트리금액": "", "대분류": "생활", "중분류": "편의점", "소분류": "바이더웨이"}, {"이용일": "20190712", "결제일": "", "금액": "41600", "포인트리금액": "", "대분류": "통신", "중분류": "", "소분류": ""}, {"이용일": "20190712", "결제일": "", "금액": "2000", "포인트리금액": "20", "대분류": "식사", "중분류": "카페", "소분류": "카페7그램"}, {"이용일": "20190713", "결제일": "", "금액": "8000", "포인트리금액": "", "대분류": "생활", "중분류": "마트", "소분류": "웰빙마트"}, {"이용일": "20190713", "결제일": "", "금액": "15000", "포인트리금액": "", "대분류": "식사", "중분류": "한식", "소분류": ""}, {"이용일": "20190714", "결제일": "", "금액": "3500", "포인트리금액": "", "대분류": "식사", "중분류": "카페", "소분류": "요거프레소"}, {"이용일": "20190714", "결제일": "", "금액": "2000", "포인트리금액": "", "대분류": "식사", "중분류": "카페", "소분류": "요거프레소"}, {"이용일": "20190714", "결제일": "", "금액": "8700", "포인트리금액": "", "대분류": "식사", "중분류": "햄버거", "소분류": "버거킹"}, {"이용일": "20190714", "결제일": "", "금액": "20200", "포인트리금액": "", "대분류": "식사", "중분류": "햄버거", "소분류": "롯데리아"}, {"이용일": "20190715", "결제일": "", "금액": "3500", "포인트리금액": "", "대분류": "식사", "중분류": "분식", "소분류": ""}, {"이용일": "20190715", "결제일": "20190718", "금액": "55400", "포인트리금액": "", "대분류": "교통", "중분류": "버스 24", "소분류": ""}, {"이용일": "20190715", "결제일": "", "금액": "-1585", "포인트리금액": "", "대분류": "기타", "중분류": "할인", "소분류": ""}, {"이용일": "20190717", "결제일": "", "금액": "3500", "포인트리금액": "", "대분류": "생활", "중분류": "편의점", "소분류": "바이더웨이"}, {"이용일": "20190717", "결제일": "", "금액": "7200", "포인트리금액": "", "대분류": "쇼핑", "중분류": "온라인", "소분류": "쿠팡"}, {"이용일": "20190718", "결제일": "", "금액": "2000", "포인트리금액": "20", "대분류": "식사", "중분류": "카페", "소분류": "카페7그램"}, {"이용일": "20190719", "결제일": "", "금액": "8000", "포인트리금액": "", "대분류": "식사", "중분류": "카페", "소분류": "아리스타커피"}, {"이용일": "20190720", "결제일": "", "금액": "11200", "포인트리금액": "", "대분류": "식사", "중분류": "카페", "소분류": "스타벅스"}, {"이용일": "20190720", "결제일": "", "금액": "-2240", "포인트리금액": "", "대분류": "기타", "중분류": "할인", "소분류": ""}, {"이용일": "20190720", "결제일": "", "금액": "6000", "포인트리금액": "", "대분류": "생활", "중분류": "오피스", "소분류": "다이소"}, {"이용일": "20190720", "결제일": "", "금액": "29500", "포인트리금액": "", "대분류": "식사", "중분류": "레스토랑", "소분류": ""}, {"이용일": "20190720", "결제일": "", "금액": "4700", "포인트리금액": "", "대분류": "생활", "중분류": "마트", "소분류": "웰빙마트"}, {"이용일": "20190720", "결제일": "", "금액": "12900", "포인트리금액": "", "대분류": "쇼핑", "중분류": "패션", "소분류": "스파오"}, {"이용일": "20190721", "결제일": "", "금액": "3300", "포인트리금액": "", "대분류": "식사", "중분류": "카페", "소분류": "서기커피"}, {"이용일": "20190722", "결제일": "", "금액": "7000", "포인트리금액": "", "대분류": "식사", "중분류": "순대", "소분류": ""}, {"이용일": "20190723", "결제일": "", "금액": "2000", "포인트리금액": "20", "대분류": "식사", "중분류": "카페", "소분류": "카페7그램"}, {"이용일": "20190725", "결제일": "", "금액": "7000", "포인트리금액": "", "대분류": "식사", "중분류": "카페", "소분류": "빽다방"}, {"이용일": "20190725", "결제일": "", "금액": "2300", "포인트리금액": "", "대분류": "생활", "중분류": "마트", "소분류": "이마트"}, {"이용일": "20190725", "결제일": "", "금액": "16000", "포인트리금액": "", "대분류": "식사", "중분류": "한식", "소분류": ""}, {"이용일": "20190726", "결제일": "", "금액": "-41600", "포인트리금액": "", "대분류": "통신", "중분류": "", "소분류": ""}, {"이용일": "20190727", "결제일": "", "금액": "44800", "포인트리금액": "448", "대분류": "생활", "중분류": "전자", "소분류": "애플"}, {"이용일": "20190727", "결제일": "", "금액": "6600", "포인트리금액": "", "대분류": "식사", "중분류": "카페", "소분류": "서기커피"}, {"이용일": "20190728", "결제일": "20190805", "금액": "5250", "포인트리금액": "", "대분류": "교통", "중분류": "지하철 4", "소분류": ""}, {"이용일": "20190728", "결제일": "", "금액": "18000", "포인트리금액": "", "대분류": "식사", "중분류": "베트남식", "소분류": ""}, {"이용일": "20190728", "결제일": "", "금액": "18900", "포인트리금액": "", "대분류": "식사", "중분류": "햄버거", "소분류": "롯데리아"}, {"이용일": "20190729", "결제일": "", "금액": "10200", "포인트리금액": "", "대분류": "쇼핑", "중분류": "온라인", "소분류": "쿠팡"}, {"이용일": "20190730", "결제일": "", "금액": "3500", "포인트리금액": "", "대분류": "생활", "중분류": "편의점", "소분류": "바이더웨이"}, {"이용일": "20190730", "결제일": "", "금액": "46000", "포인트리금액": "", "대분류": "쇼핑", "중분류": "온라인", "소분류": "쿠팡"}, {"이용일": "20190731", "결제일": "20190805", "금액": "63650", "포인트리금액": "", "대분류": "교통", "중분류": "버스 26", "소분류": ""}, {"이용일": "20190731", "결제일": "", "금액": "2000", "포인트리금액": "20", "대분류": "식사", "중분류": "카페", "소분류": "카페7그램"}]}